screenviz/__init__.py
screenviz/__main__.py
screenviz/_constants.py
screenviz/_utils.py
screenviz/compare.py
screenviz/gene.py
screenviz/idea.py
screenviz/sgrna.py
screenviz/cli/__init__.py
screenviz/cli/_compare.py
screenviz/cli/_gene.py
screenviz/cli/_idea.py
screenviz/cli/_quality_control.py
screenviz/cli/_results.py
screenviz/cli/_sgrna.py
screenviz/qc/__init__.py
screenviz/qc/app.py
screenviz/qc/correlation_matrix_card.py
screenviz/qc/histogram_membership_card.py
screenviz/qc/kde_histogram_card.py
screenviz/qc/scatter_data_card.py
screenviz/qc/utils.py
screenviz/results/__init__.py
screenviz/results/_utils.py
screenviz/results/app.py
screenviz/results/gene_card.py
screenviz/results/idea_card.py
screenviz/results/sgrna_card.py
screenviz-0.2.9.dist-info/licenses/LICENSE
screenviz-0.2.9.dist-info/METADATA
screenviz-0.2.9.dist-info/WHEEL
screenviz-0.2.9.dist-info/entry_points.txt
screenviz-0.2.9.dist-info/top_level.txt
screenviz-0.2.9.dist-info/RECORD
