Metadata-Version: 2.4
Name: screenviz
Version: 0.2.9
Summary: A tool to visualize the results of 1D CRISPR screens
Author: noam teyssier
License: MIT License
Requires-Python: >=3.11
License-File: LICENSE
Requires-Dist: dash>=2.18.1
Requires-Dist: idea-bio>=0.2.5
Requires-Dist: numpy>=1.26.4
Requires-Dist: pandas>=2.2.3
Requires-Dist: plotly>=5.24.1
Requires-Dist: pyyaml>=6.0.2
Requires-Dist: scipy>=1.14.1
Requires-Dist: dash-daq>=0.5.0
Dynamic: license-file
